aiohttp_ultrajson.py
setup.py
aiohttp_ultrajson.egg-info/PKG-INFO
aiohttp_ultrajson.egg-info/SOURCES.txt
aiohttp_ultrajson.egg-info/dependency_links.txt
aiohttp_ultrajson.egg-info/not-zip-safe
aiohttp_ultrajson.egg-info/requires.txt
aiohttp_ultrajson.egg-info/top_level.txt