Metadata-Version: 1.1
Name: aiohttp-ultrajson
Version: 0.0.1
Summary: Integrates UltraJSON with your aiohttp application.
Home-page: https://github.com/sunghyunzz/aiohttp-ultrajson
Author: sunghyunzz
Author-email: me@sunghyunzz.com
License: MIT
Platform: any
Classifier: Development Status :: 3 - Alpha
Classifier: License :: OSI Approved :: MIT License
Classifier: Intended Audience :: Developers
Classifier: Programming Language :: Python
Classifier: Programming Language :: Python :: 3
Classifier: Programming Language :: Python :: 3.5
